{"_ts":[1488327323,1488371304,1488415322],"_r":{"breakdown":{"html":{"bytes":[11695,11704,11705],"requests":[2,2,2]},"js":{"bytes":[56682,56683,56691],"requests":[6,6,6]},"css":{"bytes":[79290,79290,79290],"requests":[2,2,2]},"image":{"bytes":[63010,63010,63010],"requests":[9,9,9]},"flash":{"bytes":[0,0,0],"requests":[0,0,0]},"font":{"bytes":[0,0,0],"requests":[0,0,0]},"other":{"bytes":[0,0,0],"requests":[0,0,0]}},"date":[1488327323,1488371304,1488415322],"domElements":[1089,1089,1089],"domInteractive":[1183,1031,1169],"firstPaint":[1169,1009,1137],"fullyLoaded":[3766,3757,4210],"id":["170301_1S_PC","170301_NN_QKR","170302_X5_1EW"],"loadTime":[3302,2827,3723],"render":[1501,1501,1581],"SpeedIndex":[1526,1503,1584],"TTFB":[660,550,555],"videoFrames":[[{"_t":0,"_vc":0},{"_t":1500,"_vc":74},{"_t":1600,"_vc":99},{"_t":2100,"_vc":99},{"_t":2800,"_vc":99},{"_t":3000,"_vc":99},{"_t":3500,"_vc":100}],[{"_t":0,"_vc":0},{"_t":1500,"_vc":99},{"_t":2000,"_vc":99},{"_t":2600,"_vc":99},{"_t":3100,"_vc":100}],[{"_t":0,"_vc":0},{"_t":1600,"_vc":99},{"_t":2300,"_vc":99},{"_t":3400,"_vc":99},{"_t":4000,"_vc":100}]],"visualComplete":[3494,3096,3972]}}